bit_exp/__init__.py
bit_exp/cli.py
bit_exp/radar/ATimaging.py
bit_exp/radar/RDimaging.py
bit_exp/radar/__init__.py
bit_exp/radar/bin2mat.py
bit_exp/radar/cfar.py
bit_exp/radar/processing.py
bit_exp-0.1.1.dist-info/licenses/LICENSE
bit_exp-0.1.1.dist-info/METADATA
bit_exp-0.1.1.dist-info/WHEEL
bit_exp-0.1.1.dist-info/entry_points.txt
bit_exp-0.1.1.dist-info/top_level.txt
bit_exp-0.1.1.dist-info/RECORD
