Metadata-Version: 2.4
Name: bit_exp
Version: 0.1.1
Summary: BIT实验工具包，包含雷达信号处理等实验
Home-page: https://github.com/yourusername/bit_exp
Author: Haotian
Author-email: Haotian <your.email@example.com>
License: MIT
Project-URL: Homepage, https://github.com/yourusername/bit_exp
Project-URL: Bug Tracker, https://github.com/yourusername/bit_exp/issues
Classifier: Development Status :: 3 - Alpha
Classifier: Intended Audience :: Science/Research
Classifier: Topic :: Scientific/Engineering
Classifier: License :: OSI Approved :: MIT License
Classifier: Programming Language :: Python :: 3
Classifier: Programming Language :: Python :: 3.8
Classifier: Programming Language :: Python :: 3.9
Classifier: Programming Language :: Python :: 3.10
Classifier: Programming Language :: Python :: 3.11
Classifier: Programming Language :: Python :: 3.12
Classifier: Programming Language :: Python :: 3.13
Requires-Python: >=3.8
License-File: LICENSE
Requires-Dist: numpy
Requires-Dist: scipy
Requires-Dist: matplotlib
Requires-Dist: opencv-python
Requires-Dist: Pillow
Dynamic: author
Dynamic: home-page
Dynamic: license-file
Dynamic: requires-python
